dzira/__init__.py
dzira/api.py
dzira/betterdict.py
dzira/cli/commands.py
dzira/cli/config.py
dzira/cli/output.py
dzira-0.4.1.dist-info/LICENSE
dzira-0.4.1.dist-info/METADATA
dzira-0.4.1.dist-info/WHEEL
dzira-0.4.1.dist-info/entry_points.txt
dzira-0.4.1.dist-info/top_level.txt
dzira-0.4.1.dist-info/RECORD
