Metadata-Version: 2.1
Name: dzira
Version: 0.4.1
Summary: A cli wrapper for jira API to track sprints and manage worklogs
Author-email: Piotr Kaznowski <piotr@kazno.dev>
Project-URL: Homepage, https://github.com/caseneuve/dzira
Project-URL: Issues, https://github.com/caseneuve/dzira/issues
Project-URL: Changelog, https://github.com/caseneuve/dzira/blob/master/CHANGELOG.md
Classifier: Development Status :: 3 - Alpha
Classifier: Programming Language :: Python :: 3
Classifier: Programming Language :: Python :: 3.12
Classifier: Programming Language :: Python :: 3.11
Classifier: Programming Language :: Python :: 3.10
Classifier: Programming Language :: Python :: 3.9
Classifier: Programming Language :: Python :: 3.8
Classifier: Intended Audience :: Developers
Classifier: License :: OSI Approved :: MIT License
Classifier: Topic :: Software Development
Requires-Python: >=3.8
License-File: LICENSE
Requires-Dist: click >=8.1
Requires-Dist: jira
Requires-Dist: python-dotenv
Requires-Dist: tabulate
